quickzoom/__init__.py
quickzoom/cli.py
quickzoom/connect.py
quickzoom-0.2.2.dist-info/AUTHORS.rst
quickzoom-0.2.2.dist-info/LICENSE
quickzoom-0.2.2.dist-info/METADATA
quickzoom-0.2.2.dist-info/WHEEL
quickzoom-0.2.2.dist-info/entry_points.txt
quickzoom-0.2.2.dist-info/top_level.txt
quickzoom-0.2.2.dist-info/RECORD
