Metadata-Version: 2.1
Name: quickzoom
Version: 0.2.2
Summary: quickzoom is a python command line tool that enables you easy connecting to zoom rooms
Home-page: https://github.com/paulgolter/quickzoom
Author: Paul Golter
Author-email: paulgolter.de@gmail.com
License: MIT license
Keywords: quickzoom
Platform: UNKNOWN
Classifier: Development Status :: 2 - Pre-Alpha
Classifier: Intended Audience :: Developers
Classifier: License :: OSI Approved :: MIT License
Classifier: Natural Language :: English
Classifier: Programming Language :: Python :: 3
Classifier: Programming Language :: Python :: 3.5
Classifier: Programming Language :: Python :: 3.6
Classifier: Programming Language :: Python :: 3.7
Classifier: Programming Language :: Python :: 3.8
Requires-Python: >=3.5
